{
	"MaxHP": {
		"name": "HP",
		"icon": "SpriteOutput/UI/Avatar/Icon/IconMaxHP.png",
		"shortIcon": "IconMaxHP",
		"id": "MaxHP"
	},
	"CriticalValue": {
		"name": "CRIT Value",
		"icon": "SpriteOutput/UI/Avatar/Icon/IconCriticalDamage.png",
		"shortIcon": "IconCriticalDamage",
		"id": "CriticalValue"
	},
	"AddedRatio": {
		"name": "DMG Boost",
		"icon": "SpriteOutput/UI/Avatar/Icon/IconAttack.png",
		"shortIcon": "IconAttack",
		"id": "AddedRatio"
	},
	"Attack": {
		"name": "공격력",
		"icon": "SpriteOutput/UI/Avatar/Icon/IconAttack.png",
		"shortIcon": "IconAttack",
		"id": "Attack"
	},
	"Defence": {
		"name": "방어력",
		"icon": "SpriteOutput/UI/Avatar/Icon/IconDefence.png",
		"shortIcon": "IconDefence",
		"id": "Defence"
	},
	"Speed": {
		"name": "속도",
		"icon": "SpriteOutput/UI/Avatar/Icon/IconSpeed.png",
		"shortIcon": "IconSpeed",
		"id": "Speed"
	},
	"CriticalChance": {
		"name": "치명타 확률",
		"icon": "SpriteOutput/UI/Avatar/Icon/IconCriticalChance.png",
		"shortIcon": "IconCriticalChance",
		"id": "CriticalChance"
	},
	"CriticalDamage": {
		"name": "치명타 피해",
		"icon": "SpriteOutput/UI/Avatar/Icon/IconCriticalDamage.png",
		"shortIcon": "IconCriticalDamage",
		"id": "CriticalDamage"
	},
	"BreakDamageAddedRatio": {
		"name": "격파 특수효과",
		"icon": "SpriteOutput/UI/Avatar/Icon/IconBreakUp.png",
		"shortIcon": "IconBreakUp",
		"id": "BreakDamageAddedRatio"
	},
	"BreakDamageAddedRatioBase": {
		"name": "격파 특수효과",
		"icon": "SpriteOutput/UI/Avatar/Icon/IconBreakUp.png",
		"shortIcon": "IconBreakUp",
		"id": "BreakDamageAddedRatioBase"
	},
	"HealRatio": {
		"name": "치유량 보너스",
		"icon": "SpriteOutput/UI/Avatar/Icon/IconHealRatio.png",
		"shortIcon": "IconHealRatio",
		"id": "HealRatio"
	},
	"MaxSP": {
		"name": "에너지 최대치",
		"icon": "SpriteOutput/UI/Avatar/Icon/IconEnergyLimit.png",
		"shortIcon": "IconEnergyLimit",
		"id": "MaxSP"
	},
	"SPRatio": {
		"name": "에너지 회복효율",
		"icon": "SpriteOutput/UI/Avatar/Icon/IconEnergyRecovery.png",
		"shortIcon": "IconEnergyRecovery",
		"id": "SPRatio"
	},
	"StatusProbability": {
		"name": "효과 명중",
		"icon": "SpriteOutput/UI/Avatar/Icon/IconStatusProbability.png",
		"shortIcon": "IconStatusProbability",
		"id": "StatusProbability"
	},
	"StatusResistance": {
		"name": "효과 저항",
		"icon": "SpriteOutput/UI/Avatar/Icon/IconStatusResistance.png",
		"shortIcon": "IconStatusResistance",
		"id": "StatusResistance"
	},
	"CriticalChanceBase": {
		"name": "치명타 확률",
		"icon": "SpriteOutput/UI/Avatar/Icon/IconCriticalChance.png",
		"shortIcon": "IconCriticalChance",
		"id": "CriticalChanceBase"
	},
	"CriticalDamageBase": {
		"name": "치명타 피해",
		"icon": "SpriteOutput/UI/Avatar/Icon/IconCriticalDamage.png",
		"shortIcon": "IconCriticalDamage",
		"id": "CriticalDamageBase"
	},
	"HealRatioBase": {
		"name": "치유량 보너스",
		"icon": "SpriteOutput/UI/Avatar/Icon/IconHealRatio.png",
		"shortIcon": "IconHealRatio",
		"id": "HealRatioBase"
	},
	"StanceBreakAddedRatio": {
		"icon": "0",
		"shortIcon": "0",
		"id": "StanceBreakAddedRatio"
	},
	"SPRatioBase": {
		"name": "에너지 회복효율",
		"icon": "SpriteOutput/UI/Avatar/Icon/IconEnergyRecovery.png",
		"shortIcon": "IconEnergyRecovery",
		"id": "SPRatioBase"
	},
	"StatusProbabilityBase": {
		"name": "효과 명중",
		"icon": "SpriteOutput/UI/Avatar/Icon/IconStatusProbability.png",
		"shortIcon": "IconStatusProbability",
		"id": "StatusProbabilityBase"
	},
	"StatusResistanceBase": {
		"name": "효과 저항",
		"icon": "SpriteOutput/UI/Avatar/Icon/IconStatusResistance.png",
		"shortIcon": "IconStatusResistance",
		"id": "StatusResistanceBase"
	},
	"PhysicalAddedRatio": {
		"name": "물리 속성 피해 증가",
		"icon": "SpriteOutput/UI/Avatar/Icon/IconPhysicalAddedRatio.png",
		"shortIcon": "IconPhysicalAddedRatio",
		"id": "PhysicalAddedRatio"
	},
	"PhysicalResistance": {
		"name": "물리 속성 저항 증가",
		"icon": "SpriteOutput/UI/Avatar/Icon/IconPhysicalResistanceDelta.png",
		"shortIcon": "IconPhysicalResistanceDelta",
		"id": "PhysicalResistance"
	},
	"FireAddedRatio": {
		"name": "화염 속성 피해 증가",
		"icon": "SpriteOutput/UI/Avatar/Icon/IconFireAddedRatio.png",
		"shortIcon": "IconFireAddedRatio",
		"id": "FireAddedRatio"
	},
	"FireResistance": {
		"name": "화염 속성 저항 증가",
		"icon": "SpriteOutput/UI/Avatar/Icon/IconFireResistanceDelta.png",
		"shortIcon": "IconFireResistanceDelta",
		"id": "FireResistance"
	},
	"IceAddedRatio": {
		"name": "얼음 속성 피해 증가",
		"icon": "SpriteOutput/UI/Avatar/Icon/IconIceAddedRatio.png",
		"shortIcon": "IconIceAddedRatio",
		"id": "IceAddedRatio"
	},
	"IceResistance": {
		"name": "얼음 속성 저항 증가",
		"icon": "SpriteOutput/UI/Avatar/Icon/IconIceResistanceDelta.png",
		"shortIcon": "IconIceResistanceDelta",
		"id": "IceResistance"
	},
	"ThunderAddedRatio": {
		"name": "번개 속성 피해 증가",
		"icon": "SpriteOutput/UI/Avatar/Icon/IconThunderAddedRatio.png",
		"shortIcon": "IconThunderAddedRatio",
		"id": "ThunderAddedRatio"
	},
	"ThunderResistance": {
		"name": "번개 속성 저항 증가",
		"icon": "SpriteOutput/UI/Avatar/Icon/IconThunderResistanceDelta.png",
		"shortIcon": "IconThunderResistanceDelta",
		"id": "ThunderResistance"
	},
	"WindAddedRatio": {
		"name": "바람 속성 피해 증가",
		"icon": "SpriteOutput/UI/Avatar/Icon/IconWindAddedRatio.png",
		"shortIcon": "IconWindAddedRatio",
		"id": "WindAddedRatio"
	},
	"WindResistance": {
		"name": "바람 속성 저항 증가",
		"icon": "SpriteOutput/UI/Avatar/Icon/IconWindResistanceDelta.png",
		"shortIcon": "IconWindResistanceDelta",
		"id": "WindResistance"
	},
	"QuantumAddedRatio": {
		"name": "양자 속성 피해 증가",
		"icon": "SpriteOutput/UI/Avatar/Icon/IconQuantumAddedRatio.png",
		"shortIcon": "IconQuantumAddedRatio",
		"id": "QuantumAddedRatio"
	},
	"QuantumResistance": {
		"name": "양자 속성 저항 증가",
		"icon": "SpriteOutput/UI/Avatar/Icon/IconQuantumResistanceDelta.png",
		"shortIcon": "IconQuantumResistanceDelta",
		"id": "QuantumResistance"
	},
	"ImaginaryAddedRatio": {
		"name": "허수 속성 피해 증가",
		"icon": "SpriteOutput/UI/Avatar/Icon/IconImaginaryAddedRatio.png",
		"shortIcon": "IconImaginaryAddedRatio",
		"id": "ImaginaryAddedRatio"
	},
	"ImaginaryResistance": {
		"name": "허수 속성 저항 증가",
		"icon": "SpriteOutput/UI/Avatar/Icon/IconImaginaryResistanceDelta.png",
		"shortIcon": "IconImaginaryResistanceDelta",
		"id": "ImaginaryResistance"
	},
	"BaseHP": {
		"name": "기초 HP",
		"icon": "SpriteOutput/UI/Avatar/Icon/IconMaxHP.png",
		"shortIcon": "IconMaxHP",
		"id": "BaseHP"
	},
	"HPDelta": {
		"name": "HP",
		"icon": "SpriteOutput/UI/Avatar/Icon/IconMaxHP.png",
		"shortIcon": "IconMaxHP",
		"id": "HPDelta"
	},
	"HPAddedRatio": {
		"name": "HP",
		"icon": "SpriteOutput/UI/Avatar/Icon/IconMaxHP.png",
		"shortIcon": "IconMaxHP",
		"id": "HPAddedRatio"
	},
	"BaseAttack": {
		"name": "기초 공격력",
		"icon": "SpriteOutput/UI/Avatar/Icon/IconAttack.png",
		"shortIcon": "IconAttack",
		"id": "BaseAttack"
	},
	"AttackDelta": {
		"name": "공격력",
		"icon": "SpriteOutput/UI/Avatar/Icon/IconAttack.png",
		"shortIcon": "IconAttack",
		"id": "AttackDelta"
	},
	"AttackAddedRatio": {
		"name": "공격력",
		"icon": "SpriteOutput/UI/Avatar/Icon/IconAttack.png",
		"shortIcon": "IconAttack",
		"id": "AttackAddedRatio"
	},
	"BaseDefence": {
		"name": "기초 방어력",
		"icon": "SpriteOutput/UI/Avatar/Icon/IconDefence.png",
		"shortIcon": "IconDefence",
		"id": "BaseDefence"
	},
	"DefenceDelta": {
		"name": "방어력",
		"icon": "SpriteOutput/UI/Avatar/Icon/IconDefence.png",
		"shortIcon": "IconDefence",
		"id": "DefenceDelta"
	},
	"DefenceAddedRatio": {
		"name": "방어력",
		"icon": "SpriteOutput/UI/Avatar/Icon/IconDefence.png",
		"shortIcon": "IconDefence",
		"id": "DefenceAddedRatio"
	},
	"BaseSpeed": {
		"name": "속도",
		"icon": "SpriteOutput/UI/Avatar/Icon/IconSpeed.png",
		"shortIcon": "IconSpeed",
		"id": "BaseSpeed"
	},
	"HealTakenRatio": {
		"name": "받는 치유량 <unbreak>#1[f1]%</unbreak> 증가",
		"icon": "SpriteOutput/UI/Avatar/Icon/IconHealRatio.png",
		"shortIcon": "IconHealRatio",
		"id": "HealTakenRatio"
	},
	"PhysicalResistanceDelta": {
		"name": "물리 속성 저항 증가",
		"icon": "SpriteOutput/UI/Avatar/Icon/IconPhysicalResistanceDelta.png",
		"shortIcon": "IconPhysicalResistanceDelta",
		"id": "PhysicalResistanceDelta"
	},
	"FireResistanceDelta": {
		"name": "화염 속성 저항 증가",
		"icon": "SpriteOutput/UI/Avatar/Icon/IconFireResistanceDelta.png",
		"shortIcon": "IconFireResistanceDelta",
		"id": "FireResistanceDelta"
	},
	"IceResistanceDelta": {
		"name": "얼음 속성 저항 증가",
		"icon": "SpriteOutput/UI/Avatar/Icon/IconIceResistanceDelta.png",
		"shortIcon": "IconIceResistanceDelta",
		"id": "IceResistanceDelta"
	},
	"ThunderResistanceDelta": {
		"name": "번개 속성 저항 증가",
		"icon": "SpriteOutput/UI/Avatar/Icon/IconThunderResistanceDelta.png",
		"shortIcon": "IconThunderResistanceDelta",
		"id": "ThunderResistanceDelta"
	},
	"WindResistanceDelta": {
		"name": "바람 속성 저항 증가",
		"icon": "SpriteOutput/UI/Avatar/Icon/IconWindResistanceDelta.png",
		"shortIcon": "IconWindResistanceDelta",
		"id": "WindResistanceDelta"
	},
	"QuantumResistanceDelta": {
		"name": "양자 속성 저항 증가",
		"icon": "SpriteOutput/UI/Avatar/Icon/IconQuantumResistanceDelta.png",
		"shortIcon": "IconQuantumResistanceDelta",
		"id": "QuantumResistanceDelta"
	},
	"ImaginaryResistanceDelta": {
		"name": "허수 속성 저항 증가",
		"icon": "SpriteOutput/UI/Avatar/Icon/IconImaginaryResistanceDelta.png",
		"shortIcon": "IconImaginaryResistanceDelta",
		"id": "ImaginaryResistanceDelta"
	},
	"SpeedDelta": {
		"name": "속도",
		"icon": "SpriteOutput/UI/Avatar/Icon/IconSpeed.png",
		"shortIcon": "IconSpeed",
		"id": "SpeedDelta"
	}
}