{
  "nodes": [
    { "id": 1,  "pos": { "x": 350, "y": 400 } },
    { "id": 2,  "pos": { "x": 650, "y": 400 } },
    { "id": 3,  "pos": { "x": 500, "y": 400 } },
    { "id": 4,  "pos": { "x": 500, "y": 300 } },
    { "id": 5,  "pos": { "x": 500, "y": 500 } },
    { "id": 6,  "pos": { "x": 250, "y": 450 } },
    { "id": 7,  "pos": { "x": 750, "y": 450 } },
    { "id": 8,  "pos": { "x": 500, "y": 200 } },
    { "id": 9,  "pos": { "x": 500, "y": 600 } },
    { "id": 10, "pos": { "x": 200, "y": 550 } },
    { "id": 11, "pos": { "x": 250, "y": 650 } },
    { "id": 12, "pos": { "x": 300, "y": 750 } },
    { "id": 13, "pos": { "x": 800, "y": 550 } },
    { "id": 14, "pos": { "x": 750, "y": 650 } },
    { "id": 15, "pos": { "x": 700, "y": 750 } },
    { "id": 16, "pos": { "x": 350, "y": 200 } },
    { "id": 17, "pos": { "x": 650, "y": 200 } },
    { "id": 18, "pos": { "x": 500, "y": 700 } }
  ],
  "edges": [
    { "from": 16, "to": 8 },
    { "from": 17, "to": 8 },
    { "from": 8, "to": 4 },
    { "from": 4, "to": 3 },
    { "from": 3, "to": 5 },
    { "from": 5, "to": 9 },
    { "from": 9, "to": 18 },

    { "from": 3, "to": 1 },
    { "from": 3, "to": 2 },

    { "from": 1, "to": 6 },
    { "from": 6, "to": 10 },
    { "from": 10, "to": 11 },
    { "from": 11, "to": 12 },

    { "from": 2, "to": 7 },
    { "from": 7, "to": 13 },
    { "from": 13, "to": 14 },
    { "from": 14, "to": 15 }
  ]
}
