{
	"name": "Silvermane Cannoneer",
	"description": "A cannoneer of the Silvermane Guards who wields a portable hand cannon into battle.\nDuring combat, Silvermane Cannoneers will launch brutal chain attacks with their allies.",
	"icon": "spriteoutput/monsterfigure/Monster_1002030.png",
	"shortIcon": "Monster_1002030",
	"stats": {
		"baseAttack": 9,
		"baseDefense": 210,
		"baseHealth": 232.49998233,
		"type": "MinionLv2"
	},
	"skills": [
		{
			"id": "100203001",
			"name": "Barrage",
			"tag": "Blast",
			"type": "Ability",
			"description": "Deals minor Physical DMG to a single target and units adjacent to the target.",
			"element": "Physical",
			"attackType": "Normal",
			"params": [
				1.3,
				1
			],
			"spGain": 10,
			"delay": 1,
			"icon": "spriteoutput/skillicons/avatar/1001/skillicon_1001_maze.png",
			"shortIcon": "skillicon_1001_maze"
		},
		{
			"id": "100203002",
			"name": "Covering Support",
			"tag": "Support",
			"type": "Ability",
			"description": "Provides support to a friendly unit. When this unit attacks, it performs a Follow-up ATK that deals minor Physical DMG to the attacked target and units adjacent to the target.",
			"element": "Physical",
			"attackType": "Normal",
			"params": [],
			"spGain": 0,
			"delay": 1,
			"icon": "spriteoutput/skillicons/avatar/1001/skillicon_1001_maze.png",
			"shortIcon": "skillicon_1001_maze"
		},
		{
			"id": "100203003",
			"name": "Covering Support",
			"tag": "Talent",
			"type": "Talent",
			"description": "Provides support to a friendly unit. When this unit attacks, it performs a Follow-up ATK that deals minor Physical DMG to the attacked target and units adjacent to the target.",
			"element": "Physical",
			"attackType": "Normal",
			"params": [
				2.2,
				1.5
			],
			"spGain": 12,
			"delay": 1,
			"icon": "spriteoutput/skillicons/avatar/1001/skillicon_1001_maze.png",
			"shortIcon": "skillicon_1001_maze"
		}
	],
	"resistance": [
		{
			"element": "Fire",
			"value": 0.2
		},
		{
			"element": "Thunder",
			"value": 0.2
		},
		{
			"element": "Wind",
			"value": 0.2
		},
		{
			"element": "Quantum",
			"value": 0.2
		}
	],
	"weakness": [
		"Physical",
		"Ice",
		"Imaginary"
	],
	"drops": {
		"avatarExpReward": 36,
		"itemList": [
			{
				"id": 2,
				"count": 1
			},
			{
				"id": 112001,
				"count": 1
			},
			{
				"id": 181005,
				"count": 1
			}
		]
	},
	"rank": "MinionLv2",
	"stanceType": "Physical",
	"id": "100203008"
}