{
	"name": "Abundant Ebon Deer",
	"description": "An auspicious spiritual beast wrought into being by the Ambrosial Arbor and protects its roots. Its arrival brings along exuberant vegetation and promises good fortune.\nOnce destroyed during ancient wars, the Ambrosial Arbor is mended by the Stellaron and finally revives. Rare creatures and legendary beasts made by celestials of the past all return to this world, like an old dream coming alive again.",
	"icon": "spriteoutput/monsterfigure/Monster_2024010.png",
	"shortIcon": "Monster_2024010",
	"stats": {
		"baseAttack": 18,
		"baseDefense": 210,
		"baseHealth": 6974.99907,
		"type": "LittleBoss"
	},
	"skills": [
		{
			"id": "202401401",
			"name": "Pedicel: Wintry Wind",
			"tag": "Summon",
			"type": "Ability",
			"description": "Summons Ambrosial Arbor branch \"Twig of Wintry Wind\"",
			"element": "Physical",
			"attackType": "Normal",
			"params": [
				0.5
			],
			"spGain": 0,
			"delay": 1,
			"icon": "spriteoutput/skillicons/avatar/1001/skillicon_1001_maze.png",
			"shortIcon": "skillicon_1001_maze"
		},
		{
			"id": "202401402",
			"name": "Pedicel: Marple Leaf",
			"tag": "Summon",
			"type": "Ability",
			"description": "Summons Ambrosial Arbor branch \"Twig of Marple Leaf\"",
			"element": "Physical",
			"attackType": "Normal",
			"params": [
				0
			],
			"spGain": 0,
			"delay": 1,
			"icon": "spriteoutput/skillicons/avatar/1001/skillicon_1001_maze.png",
			"shortIcon": "skillicon_1001_maze"
		},
		{
			"id": "202401403",
			"name": "Pedicel: Glorious Blooms",
			"tag": "Summon",
			"type": "Ability",
			"description": "Summons Ambrosial Arbor branch \"Twig of Glorious Blooms\"",
			"element": "Physical",
			"attackType": "Normal",
			"params": [
				1
			],
			"spGain": 0,
			"delay": 1,
			"icon": "spriteoutput/skillicons/avatar/1001/skillicon_1001_maze.png",
			"shortIcon": "skillicon_1001_maze"
		},
		{
			"id": "202401404",
			"name": "Pedicel: Lavish Fruits",
			"tag": "Summon",
			"type": "Ability",
			"description": "Summons Ambrosial Arbor branch \"Twig of Lavish Fruits.\"",
			"element": "Physical",
			"attackType": "Normal",
			"params": [
				0
			],
			"spGain": 0,
			"delay": 1,
			"icon": "spriteoutput/skillicons/avatar/1001/skillicon_1001_maze.png",
			"shortIcon": "skillicon_1001_maze"
		},
		{
			"id": "202401405",
			"name": "Wavering Bleat",
			"tag": "Single Target",
			"type": "Ability",
			"description": "Deals Lightning DMG to a single target.",
			"element": "Thunder",
			"attackType": "Normal",
			"params": [
				3.5
			],
			"spGain": 20,
			"delay": 1,
			"icon": "spriteoutput/skillicons/avatar/1001/skillicon_1001_maze.png",
			"shortIcon": "skillicon_1001_maze"
		},
		{
			"id": "202401406",
			"name": "Caress of Wind",
			"tag": "AoE ATK",
			"type": "Ability",
			"description": "Deals minor Wind DMG to all targets.",
			"element": "Wind",
			"attackType": "Normal",
			"params": [
				2.8
			],
			"spGain": 15,
			"delay": 1,
			"icon": "spriteoutput/skillicons/avatar/1001/skillicon_1001_maze.png",
			"shortIcon": "skillicon_1001_maze"
		},
		{
			"id": "202401407",
			"name": "Hardy Leaf Sheath",
			"tag": "Defense",
			"type": "Ability",
			"description": "Increases DEF. Toughness cannot be reduced.",
			"element": "Physical",
			"attackType": "Normal",
			"params": [
				2,
				1
			],
			"spGain": 0,
			"delay": 1,
			"icon": "spriteoutput/skillicons/avatar/1001/skillicon_1001_maze.png",
			"shortIcon": "skillicon_1001_maze"
		},
		{
			"id": "202401408",
			"name": "Flamboyant Gore",
			"tag": "AoE ATK",
			"type": "Ability",
			"description": "Uses this ability immediately when there are 2 Lavish Fruits on the field. Deals Lightning DMG to all targets. Deals more damage for every \"Ambrosial Arbor Branches\" on the field. After the ability is used, remove all \"Ambrosial Arbor Branches\" on the field.",
			"element": "Thunder",
			"attackType": "Normal",
			"params": [
				3.5,
				0.25
			],
			"spGain": 20,
			"delay": 1,
			"icon": "spriteoutput/skillicons/avatar/1001/skillicon_1001_maze.png",
			"shortIcon": "skillicon_1001_maze"
		},
		{
			"id": "202401409",
			"name": "Back to Life",
			"tag": "Restore",
			"type": "Ability",
			"description": "",
			"element": "Physical",
			"attackType": "Normal",
			"params": [],
			"spGain": 0,
			"delay": 1,
			"icon": "spriteoutput/skillicons/avatar/1001/skillicon_1001_maze.png",
			"shortIcon": "skillicon_1001_maze"
		}
	],
	"resistance": [
		{
			"element": "Physical",
			"value": 0.2
		},
		{
			"element": "Thunder",
			"value": 0.4
		},
		{
			"element": "Wind",
			"value": 0.4
		},
		{
			"element": "Imaginary",
			"value": 0.2
		}
	],
	"weakness": [
		"Fire",
		"Ice",
		"Quantum"
	],
	"drops": {
		"avatarExpReward": 0,
		"itemList": []
	},
	"rank": "LittleBoss",
	"stanceType": "Physical",
	"id": "202401404"
}