{
	"name": "The Herta",
	"description": "Esteemed Genius Society 83, human, female, young, beautiful, attractive.\nIt's said that she lives in the far edge of the Cosmos, almost never leaving. Sounds like her appearance this time...\n...must be for some issue that requires a personal touch, right?",
	"rarity": "SuperRare",
	"avatarType": "Mage",
	"element": "Ice",
	"stats": {
		"maxHP": 1164.2399999999998,
		"maxATK": 679.1400000000001,
		"maxDEF": 485.1,
		"SPD": 99,
		"TNT": 75,
		"CR": 0.05,
		"CDMG": 0.5
	},
	"icon": "spriteoutput/avatardrawcard/1401.png",
	"shortIcon": "1401",
	"drawIcon": "spriteoutput/avatardrawcardresult/1401.png",
	"skills": [
		{
			"name": "Did You Get It",
			"tag": "Single Target",
			"type": "Basic ATK",
			"description": "Deals Ice DMG equal to ****1[i]%**** of The Herta's ATK to one designated enemy.",
			"regen": 20,
			"er": 0,
			"break": [
				30,
				0,
				0
			],
			"icon": "spriteoutput/skillicons/avatar/1401/SkillIcon_1401_Normal.png",
			"shortIcon": "SkillIcon_1401_Normal",
			"id": "140101",
			"params": {
				"lv1": [
					0.5,
					3,
					1,
					0.3
				],
				"lv2": [
					0.6,
					3,
					1,
					0.3
				],
				"lv3": [
					0.7,
					3,
					1,
					0.3
				],
				"lv4": [
					0.8,
					3,
					1,
					0.3
				],
				"lv5": [
					0.9,
					3,
					1,
					0.3
				],
				"lv6": [
					1,
					3,
					1,
					0.3
				],
				"lv7": [
					1.1,
					3,
					1,
					0.3
				],
				"lv8": [
					1.2,
					3,
					1,
					0.3
				],
				"lv9": [
					1.3,
					3,
					1,
					0.3
				],
				"lv10": [
					1.4,
					3,
					1,
					0.3
				]
			},
			"promotion": {
				"lv1": [],
				"lv2": [
					{
						"ItemID": 2,
						"ItemNum": 5000
					},
					{
						"ItemID": 110201,
						"ItemNum": 3
					},
					{
						"ItemID": 111001,
						"ItemNum": 6
					}
				],
				"lv3": [
					{
						"ItemID": 2,
						"ItemNum": 10000
					},
					{
						"ItemID": 110202,
						"ItemNum": 3
					},
					{
						"ItemID": 111002,
						"ItemNum": 3
					}
				],
				"lv4": [
					{
						"ItemID": 2,
						"ItemNum": 20000
					},
					{
						"ItemID": 110202,
						"ItemNum": 5
					},
					{
						"ItemID": 111002,
						"ItemNum": 4
					}
				],
				"lv5": [
					{
						"ItemID": 2,
						"ItemNum": 45000
					},
					{
						"ItemID": 110203,
						"ItemNum": 3
					},
					{
						"ItemID": 111003,
						"ItemNum": 3
					}
				],
				"lv6": [
					{
						"ItemID": 2,
						"ItemNum": 160000
					},
					{
						"ItemID": 110203,
						"ItemNum": 8
					},
					{
						"ItemID": 111003,
						"ItemNum": 4
					}
				]
			}
		},
		{
			"name": "Big Brain Energy",
			"tag": "Blast",
			"type": "Skill",
			"description": "Deals Ice DMG equal to ****1[i]%**** of The Herta's ATK to one designated enemy, and inflicts **2[i]** stack(s) of \"Interpretation.\" Deals Ice DMG equal to ****1[i]%**** of The Herta's ATK to the targets hit by this instance of Skill and their respective adjacent targets. This effect can repeat 2 times.",
			"regen": 30,
			"er": 0,
			"break": [
				45,
				0,
				30
			],
			"icon": "spriteoutput/skillicons/avatar/1401/SkillIcon_1401_BP.png",
			"shortIcon": "SkillIcon_1401_BP",
			"id": "140102",
			"params": {
				"lv1": [
					0.35,
					1
				],
				"lv2": [
					0.385,
					1
				],
				"lv3": [
					0.42,
					1
				],
				"lv4": [
					0.455,
					1
				],
				"lv5": [
					0.49,
					1
				],
				"lv6": [
					0.525,
					1
				],
				"lv7": [
					0.56875,
					1
				],
				"lv8": [
					0.6125,
					1
				],
				"lv9": [
					0.65625,
					1
				],
				"lv10": [
					0.7,
					1
				],
				"lv11": [
					0.735,
					1
				],
				"lv12": [
					0.77,
					1
				],
				"lv13": [
					0.805,
					1
				],
				"lv14": [
					0.84,
					1
				],
				"lv15": [
					0.875,
					1
				]
			},
			"promotion": {
				"lv1": [],
				"lv2": [
					{
						"ItemID": 2,
						"ItemNum": 2500
					},
					{
						"ItemID": 111001,
						"ItemNum": 3
					}
				],
				"lv3": [
					{
						"ItemID": 2,
						"ItemNum": 5000
					},
					{
						"ItemID": 110201,
						"ItemNum": 3
					},
					{
						"ItemID": 111001,
						"ItemNum": 6
					}
				],
				"lv4": [
					{
						"ItemID": 2,
						"ItemNum": 10000
					},
					{
						"ItemID": 110202,
						"ItemNum": 3
					},
					{
						"ItemID": 111002,
						"ItemNum": 3
					}
				],
				"lv5": [
					{
						"ItemID": 2,
						"ItemNum": 20000
					},
					{
						"ItemID": 110202,
						"ItemNum": 5
					},
					{
						"ItemID": 111002,
						"ItemNum": 4
					}
				],
				"lv6": [
					{
						"ItemID": 2,
						"ItemNum": 30000
					},
					{
						"ItemID": 110202,
						"ItemNum": 7
					},
					{
						"ItemID": 111002,
						"ItemNum": 6
					}
				],
				"lv7": [
					{
						"ItemID": 2,
						"ItemNum": 45000
					},
					{
						"ItemID": 110203,
						"ItemNum": 3
					},
					{
						"ItemID": 111003,
						"ItemNum": 3
					}
				],
				"lv8": [
					{
						"ItemID": 2,
						"ItemNum": 80000
					},
					{
						"ItemID": 110203,
						"ItemNum": 5
					},
					{
						"ItemID": 110506,
						"ItemNum": 1
					},
					{
						"ItemID": 111003,
						"ItemNum": 4
					}
				],
				"lv9": [
					{
						"ItemID": 2,
						"ItemNum": 160000
					},
					{
						"ItemID": 110203,
						"ItemNum": 8
					},
					{
						"ItemID": 241,
						"ItemNum": 1
					},
					{
						"ItemID": 110506,
						"ItemNum": 1
					}
				],
				"lv10": [
					{
						"ItemID": 2,
						"ItemNum": 300000
					},
					{
						"ItemID": 110203,
						"ItemNum": 14
					},
					{
						"ItemID": 241,
						"ItemNum": 1
					},
					{
						"ItemID": 110506,
						"ItemNum": 1
					}
				]
			}
		},
		{
			"name": "<unbreak>Told Ya!</unbreak> <unbreak>Magic Happens</unbreak>",
			"tag": "AoE",
			"type": "Ultimate",
			"description": "Rearranges the numbers of \"Interpretation\" stacks on all enemies, prioritizing the transfer of the higher numbers of \"Interpretation\" stacks to Elite-level targets and above. Then, deals Ice DMG equal to ****1[i]%**** of The Herta's ATK to all enemies. When using Ultimate, increases The Herta's ATK by ****4[i]%****, lasting for **5[i]** turn(s). After the use, The Herta immediately takes action and gains 1 stack of \"Inspiration.\" \"Inspiration\" can stack up to **6[i]** time(s). While having \"Inspiration,\" enhances Skill to \"Hear Me Out.\"",
			"regen": 5,
			"er": 220,
			"break": [
				0,
				60,
				0
			],
			"icon": "spriteoutput/skillicons/avatar/1401/SkillIcon_1401_Ultra.png",
			"shortIcon": "SkillIcon_1401_Ultra",
			"id": "140103",
			"params": {
				"lv1": [
					1,
					2,
					1,
					0.4,
					3,
					4
				],
				"lv2": [
					1.1,
					2,
					1,
					0.44,
					3,
					4
				],
				"lv3": [
					1.2,
					2,
					1,
					0.48,
					3,
					4
				],
				"lv4": [
					1.3,
					2,
					1,
					0.52,
					3,
					4
				],
				"lv5": [
					1.4,
					2,
					1,
					0.56,
					3,
					4
				],
				"lv6": [
					1.5,
					2,
					1,
					0.6,
					3,
					4
				],
				"lv7": [
					1.625,
					2,
					1,
					0.65,
					3,
					4
				],
				"lv8": [
					1.75,
					2,
					1,
					0.7,
					3,
					4
				],
				"lv9": [
					1.875,
					2,
					1,
					0.75,
					3,
					4
				],
				"lv10": [
					2,
					2,
					1,
					0.8,
					3,
					4
				],
				"lv11": [
					2.1,
					2,
					1,
					0.84,
					3,
					4
				],
				"lv12": [
					2.2,
					2,
					1,
					0.88,
					3,
					4
				],
				"lv13": [
					2.3,
					2,
					1,
					0.92,
					3,
					4
				],
				"lv14": [
					2.4,
					2,
					1,
					0.96,
					3,
					4
				],
				"lv15": [
					2.5,
					2,
					1,
					1,
					3,
					4
				]
			},
			"promotion": {
				"lv1": [],
				"lv2": [
					{
						"ItemID": 2,
						"ItemNum": 2500
					},
					{
						"ItemID": 111001,
						"ItemNum": 3
					}
				],
				"lv3": [
					{
						"ItemID": 2,
						"ItemNum": 5000
					},
					{
						"ItemID": 110201,
						"ItemNum": 3
					},
					{
						"ItemID": 111001,
						"ItemNum": 6
					}
				],
				"lv4": [
					{
						"ItemID": 2,
						"ItemNum": 10000
					},
					{
						"ItemID": 110202,
						"ItemNum": 3
					},
					{
						"ItemID": 111002,
						"ItemNum": 3
					}
				],
				"lv5": [
					{
						"ItemID": 2,
						"ItemNum": 20000
					},
					{
						"ItemID": 110202,
						"ItemNum": 5
					},
					{
						"ItemID": 111002,
						"ItemNum": 4
					}
				],
				"lv6": [
					{
						"ItemID": 2,
						"ItemNum": 30000
					},
					{
						"ItemID": 110202,
						"ItemNum": 7
					},
					{
						"ItemID": 111002,
						"ItemNum": 6
					}
				],
				"lv7": [
					{
						"ItemID": 2,
						"ItemNum": 45000
					},
					{
						"ItemID": 110203,
						"ItemNum": 3
					},
					{
						"ItemID": 111003,
						"ItemNum": 3
					}
				],
				"lv8": [
					{
						"ItemID": 2,
						"ItemNum": 80000
					},
					{
						"ItemID": 110203,
						"ItemNum": 5
					},
					{
						"ItemID": 110506,
						"ItemNum": 1
					},
					{
						"ItemID": 111003,
						"ItemNum": 4
					}
				],
				"lv9": [
					{
						"ItemID": 2,
						"ItemNum": 160000
					},
					{
						"ItemID": 110203,
						"ItemNum": 8
					},
					{
						"ItemID": 241,
						"ItemNum": 1
					},
					{
						"ItemID": 110506,
						"ItemNum": 1
					}
				],
				"lv10": [
					{
						"ItemID": 2,
						"ItemNum": 300000
					},
					{
						"ItemID": 110203,
						"ItemNum": 14
					},
					{
						"ItemID": 241,
						"ItemNum": 1
					},
					{
						"ItemID": 110506,
						"ItemNum": 1
					}
				]
			}
		},
		{
			"name": "Hand Them Over",
			"tag": "Enhance",
			"type": "Talent",
			"description": "When enemy targets enter battle, The Herta inflicts 1 stack of \"Interpretation\" on them. At the start of each wave, applies **6[i]** stack(s) of \"Interpretation\" to a random enemy target, prioritizing Elite-level targets and above. When the Enhanced Skill's primary target has \"Interpretation,\" the multiplier for the DMG dealt increases, with each stack granting an increase of ****1[f1]%****/****2[f1]%**** on the primary target/other targets respectively. If 2 or more characters follow the Path of Erudition in the team, each stack grants an additional increase of ****1[f1]%****/****2[f1]%**** on the primary target/other targets respectively. \"Interpretation\" can stack up to **3[i]** time(s). When using the Enhanced Skill, resets the number of \"Interpretation\" stacks on the primary target to 1. After the enemy target leaves the field or gets defeated by any unit, \"Interpretation\" will be transferred, prioritizing the transfer to Elite-level targets and above.",
			"regen": 30,
			"er": 0,
			"break": [
				0,
				0,
				0
			],
			"icon": "spriteoutput/skillicons/avatar/1401/SkillIcon_1401_Passive.png",
			"shortIcon": "SkillIcon_1401_Passive",
			"id": "140104",
			"params": {
				"lv1": [
					0.04,
					0.02,
					42,
					1,
					42,
					25
				],
				"lv2": [
					0.044,
					0.022,
					42,
					1,
					42,
					25
				],
				"lv3": [
					0.048,
					0.024,
					42,
					1,
					42,
					25
				],
				"lv4": [
					0.052,
					0.026,
					42,
					1,
					42,
					25
				],
				"lv5": [
					0.055999998,
					0.027999999,
					42,
					1,
					42,
					25
				],
				"lv6": [
					0.06,
					0.03,
					42,
					1,
					42,
					25
				],
				"lv7": [
					0.065,
					0.0325,
					42,
					1,
					42,
					25
				],
				"lv8": [
					0.07,
					0.035,
					42,
					1,
					42,
					25
				],
				"lv9": [
					0.075,
					0.0375,
					42,
					1,
					42,
					25
				],
				"lv10": [
					0.08,
					0.04,
					42,
					1,
					42,
					25
				],
				"lv11": [
					0.084,
					0.042,
					42,
					1,
					42,
					25
				],
				"lv12": [
					0.088,
					0.044,
					42,
					1,
					42,
					25
				],
				"lv13": [
					0.092,
					0.046,
					42,
					1,
					42,
					25
				],
				"lv14": [
					0.096,
					0.048,
					42,
					1,
					42,
					25
				],
				"lv15": [
					0.1,
					0.05,
					42,
					1,
					42,
					25
				]
			},
			"promotion": {
				"lv1": [],
				"lv2": [
					{
						"ItemID": 2,
						"ItemNum": 2500
					},
					{
						"ItemID": 111001,
						"ItemNum": 3
					}
				],
				"lv3": [
					{
						"ItemID": 2,
						"ItemNum": 5000
					},
					{
						"ItemID": 110201,
						"ItemNum": 3
					},
					{
						"ItemID": 111001,
						"ItemNum": 6
					}
				],
				"lv4": [
					{
						"ItemID": 2,
						"ItemNum": 10000
					},
					{
						"ItemID": 110202,
						"ItemNum": 3
					},
					{
						"ItemID": 111002,
						"ItemNum": 3
					}
				],
				"lv5": [
					{
						"ItemID": 2,
						"ItemNum": 20000
					},
					{
						"ItemID": 110202,
						"ItemNum": 5
					},
					{
						"ItemID": 111002,
						"ItemNum": 4
					}
				],
				"lv6": [
					{
						"ItemID": 2,
						"ItemNum": 30000
					},
					{
						"ItemID": 110202,
						"ItemNum": 7
					},
					{
						"ItemID": 111002,
						"ItemNum": 6
					}
				],
				"lv7": [
					{
						"ItemID": 2,
						"ItemNum": 45000
					},
					{
						"ItemID": 110203,
						"ItemNum": 3
					},
					{
						"ItemID": 111003,
						"ItemNum": 3
					}
				],
				"lv8": [
					{
						"ItemID": 2,
						"ItemNum": 80000
					},
					{
						"ItemID": 110203,
						"ItemNum": 5
					},
					{
						"ItemID": 110506,
						"ItemNum": 1
					},
					{
						"ItemID": 111003,
						"ItemNum": 4
					}
				],
				"lv9": [
					{
						"ItemID": 2,
						"ItemNum": 160000
					},
					{
						"ItemID": 110203,
						"ItemNum": 8
					},
					{
						"ItemID": 241,
						"ItemNum": 1
					},
					{
						"ItemID": 110506,
						"ItemNum": 1
					}
				],
				"lv10": [
					{
						"ItemID": 2,
						"ItemNum": 300000
					},
					{
						"ItemID": 110203,
						"ItemNum": 14
					},
					{
						"ItemID": 241,
						"ItemNum": 1
					},
					{
						"ItemID": 110506,
						"ItemNum": 1
					}
				]
			}
		},
		{
			"name": "Attack",
			"tag": "",
			"type": "",
			"description": "Attacks an enemy, and after entering combat, reduces their Toughness of the corresponding Type.",
			"regen": 0,
			"er": 0,
			"break": [
				30,
				0,
				0
			],
			"icon": "spriteoutput/skillicons/avatar/1401/SkillIcon_1401_Normal.png",
			"shortIcon": "SkillIcon_1401_Normal",
			"id": "140106",
			"params": {
				"lv1": []
			}
		},
		{
			"name": "Vibe Checker",
			"tag": "Enhance",
			"type": "Technique",
			"description": "After using Technique, increases The Herta's ATK by **1[i]%** at the start of the next battle, lasting for **2[i]** turn(s).\nIf there are Basic Treasures in this current map, using Technique can mark up to **3[i]** Basic Treasures' locations.\nAfter entering battle by using Technique in Simulated Universe or Divergent Universe, at the start of each wave, deals **True DMG** to enemy targets lower than Elite-level by an amount equal to **4[i]%** of the targets' Max HP, and deals **True DMG** to enemy targets at Elite-level and above by an amount equal to **5[i]%** of the targets' Max HP.",
			"regen": 0,
			"er": 0,
			"break": [
				0,
				0,
				0
			],
			"icon": "spriteoutput/skillicons/avatar/1401/SkillIcon_1401_Maze.png",
			"shortIcon": "SkillIcon_1401_Maze",
			"id": "140107",
			"params": {
				"lv1": [
					0.6,
					2,
					3,
					0.99,
					0.3,
					25
				]
			}
		},
		{
			"name": "Hear Me Out",
			"tag": "AoE",
			"type": "Skill",
			"description": "Consumes 1 stack of \"Inspiration.\" Deals Ice DMG equal to ****1[i]%**** of The Herta's ATK to one designated enemy and inflicts **2[i]** stack(s) of \"Interpretation.\" Deals Ice DMG equal to ****1[i]%**** of The Herta's ATK to the targets hit by this instance of Skill and their respective adjacent targets, repeating 2 times. At the end, deals Ice DMG equal to ****3[i]%**** of The Herta's ATK to all enemies.",
			"regen": 30,
			"er": 0,
			"break": [
				60,
				0,
				30
			],
			"icon": "spriteoutput/skillicons/avatar/1401/SkillIcon_1401_BP02.png",
			"shortIcon": "SkillIcon_1401_BP02",
			"id": "140109",
			"params": {
				"lv1": [
					0.4,
					1,
					0.2
				],
				"lv2": [
					0.44,
					1,
					0.22
				],
				"lv3": [
					0.48,
					1,
					0.24
				],
				"lv4": [
					0.52,
					1,
					0.26
				],
				"lv5": [
					0.56,
					1,
					0.28
				],
				"lv6": [
					0.6,
					1,
					0.3
				],
				"lv7": [
					0.65,
					1,
					0.325
				],
				"lv8": [
					0.7,
					1,
					0.35
				],
				"lv9": [
					0.75,
					1,
					0.375
				],
				"lv10": [
					0.8,
					1,
					0.4
				],
				"lv11": [
					0.84,
					1,
					0.42
				],
				"lv12": [
					0.88,
					1,
					0.44
				],
				"lv13": [
					0.92,
					1,
					0.46
				],
				"lv14": [
					0.96,
					1,
					0.48
				],
				"lv15": [
					1,
					1,
					0.5
				]
			},
			"promotion": {
				"lv1": [],
				"lv2": [
					{
						"ItemID": 2,
						"ItemNum": 2500
					},
					{
						"ItemID": 111001,
						"ItemNum": 3
					}
				],
				"lv3": [
					{
						"ItemID": 2,
						"ItemNum": 5000
					},
					{
						"ItemID": 110201,
						"ItemNum": 3
					},
					{
						"ItemID": 111001,
						"ItemNum": 6
					}
				],
				"lv4": [
					{
						"ItemID": 2,
						"ItemNum": 10000
					},
					{
						"ItemID": 110202,
						"ItemNum": 3
					},
					{
						"ItemID": 111002,
						"ItemNum": 3
					}
				],
				"lv5": [
					{
						"ItemID": 2,
						"ItemNum": 20000
					},
					{
						"ItemID": 110202,
						"ItemNum": 5
					},
					{
						"ItemID": 111002,
						"ItemNum": 4
					}
				],
				"lv6": [
					{
						"ItemID": 2,
						"ItemNum": 30000
					},
					{
						"ItemID": 110202,
						"ItemNum": 7
					},
					{
						"ItemID": 111002,
						"ItemNum": 6
					}
				],
				"lv7": [
					{
						"ItemID": 2,
						"ItemNum": 45000
					},
					{
						"ItemID": 110203,
						"ItemNum": 3
					},
					{
						"ItemID": 111003,
						"ItemNum": 3
					}
				],
				"lv8": [
					{
						"ItemID": 2,
						"ItemNum": 80000
					},
					{
						"ItemID": 110203,
						"ItemNum": 5
					},
					{
						"ItemID": 110506,
						"ItemNum": 1
					},
					{
						"ItemID": 111003,
						"ItemNum": 4
					}
				],
				"lv9": [
					{
						"ItemID": 2,
						"ItemNum": 160000
					},
					{
						"ItemID": 110203,
						"ItemNum": 8
					},
					{
						"ItemID": 241,
						"ItemNum": 1
					},
					{
						"ItemID": 110506,
						"ItemNum": 1
					}
				],
				"lv10": [
					{
						"ItemID": 2,
						"ItemNum": 300000
					},
					{
						"ItemID": 110203,
						"ItemNum": 14
					},
					{
						"ItemID": 241,
						"ItemNum": 1
					},
					{
						"ItemID": 110506,
						"ItemNum": 1
					}
				]
			}
		}
	],
	"promos": {
		"basicPromo": {
			"2": 240000,
			"110201": 3,
			"110202": 8,
			"110203": 11,
			"111001": 6,
			"111002": 7,
			"111003": 7
		},
		"skillPromo": {
			"2": 652500,
			"241": 2,
			"110201": 3,
			"110202": 15,
			"110203": 30,
			"110506": 3,
			"111001": 9,
			"111002": 13,
			"111003": 7
		},
		"ultPromo": {
			"2": 652500,
			"241": 2,
			"110201": 3,
			"110202": 15,
			"110203": 30,
			"110506": 3,
			"111001": 9,
			"111002": 13,
			"111003": 7
		},
		"talentPromo": {
			"2": 652500,
			"241": 2,
			"110201": 3,
			"110202": 15,
			"110203": 30,
			"110506": 3,
			"111001": 9,
			"111002": 13,
			"111003": 7
		}
	},
	"promotion": {
		"2": 308000,
		"110423": 65,
		"111001": 15,
		"111002": 15,
		"111003": 15
	},
	"treePromotion": {
		"2": 802500,
		"241": 2,
		"110201": 6,
		"110202": 16,
		"110203": 38,
		"110506": 3,
		"111001": 8,
		"111002": 10,
		"111003": 30
	},
	"maxPromo": {
		"2": 3308000,
		"241": 8,
		"110201": 18,
		"110202": 69,
		"110203": 139,
		"110423": 65,
		"110506": 12,
		"111001": 56,
		"111002": 71,
		"111003": 73
	},
	"exp": 5797920,
	"outfits": [],
	"tree": [
		{
			"name": "Did You Get It",
			"description": "Deals Ice DMG equal to ****1[i]%**** of The Herta's ATK to one designated enemy.",
			"avatar": 1401,
			"type": 2,
			"pos": {
				"point": "01",
				"prePoint": []
			},
			"icon": "spriteoutput/skillicons/avatar/1401/SkillIcon_1401_Normal.png",
			"shortIcon": "SkillIcon_1401_Normal",
			"promotion": {
				"2": 240000,
				"110201": 3,
				"110202": 8,
				"110203": 11,
				"111001": 6,
				"111002": 7,
				"111003": 7
			},
			"params": [
				1.4,
				3,
				1,
				0.3
			],
			"requiredLevel": 0,
			"requiredPromotion": 6,
			"status": [],
			"baseSkill": [
				140101
			],
			"id": "1401001"
		},
		{
			"name": "Big Brain Energy",
			"description": "Deals Ice DMG equal to ****1[i]%**** of The Herta's ATK to one designated enemy, and inflicts **2[i]** stack(s) of \"Interpretation.\" Deals Ice DMG equal to ****1[i]%**** of The Herta's ATK to the targets hit by this instance of Skill and their respective adjacent targets. This effect can repeat 2 times.",
			"avatar": 1401,
			"type": 2,
			"pos": {
				"point": "02",
				"prePoint": []
			},
			"icon": "spriteoutput/skillicons/avatar/1401/SkillIcon_1401_BP.png",
			"shortIcon": "SkillIcon_1401_BP",
			"promotion": {
				"2": 652500,
				"241": 2,
				"110201": 3,
				"110202": 15,
				"110203": 30,
				"110506": 3,
				"111001": 9,
				"111002": 13,
				"111003": 7
			},
			"params": [
				0.875,
				1
			],
			"requiredLevel": 0,
			"requiredPromotion": 6,
			"status": [],
			"baseSkill": [
				140102,
				140109
			],
			"id": "1401002"
		},
		{
			"name": "<unbreak>Told Ya!</unbreak> <unbreak>Magic Happens</unbreak>",
			"description": "Rearranges the numbers of \"Interpretation\" stacks on all enemies, prioritizing the transfer of the higher numbers of \"Interpretation\" stacks to Elite-level targets and above. Then, deals Ice DMG equal to ****1[i]%**** of The Herta's ATK to all enemies. When using Ultimate, increases The Herta's ATK by ****4[i]%****, lasting for **5[i]** turn(s). After the use, The Herta immediately takes action and gains 1 stack of \"Inspiration.\" \"Inspiration\" can stack up to **6[i]** time(s). While having \"Inspiration,\" enhances Skill to \"Hear Me Out.\"",
			"avatar": 1401,
			"type": 2,
			"pos": {
				"point": "03",
				"prePoint": []
			},
			"icon": "spriteoutput/skillicons/avatar/1401/SkillIcon_1401_Ultra.png",
			"shortIcon": "SkillIcon_1401_Ultra",
			"promotion": {
				"2": 652500,
				"241": 2,
				"110201": 3,
				"110202": 15,
				"110203": 30,
				"110506": 3,
				"111001": 9,
				"111002": 13,
				"111003": 7
			},
			"params": [
				2.5,
				2,
				1,
				1,
				3,
				4
			],
			"requiredLevel": 0,
			"requiredPromotion": 6,
			"status": [],
			"baseSkill": [
				140103
			],
			"id": "1401003"
		},
		{
			"name": "Hand Them Over",
			"description": "When enemy targets enter battle, The Herta inflicts 1 stack of \"Interpretation\" on them. At the start of each wave, applies **6[i]** stack(s) of \"Interpretation\" to a random enemy target, prioritizing Elite-level targets and above. When the Enhanced Skill's primary target has \"Interpretation,\" the multiplier for the DMG dealt increases, with each stack granting an increase of ****1[f1]%****/****2[f1]%**** on the primary target/other targets respectively. If 2 or more characters follow the Path of Erudition in the team, each stack grants an additional increase of ****1[f1]%****/****2[f1]%**** on the primary target/other targets respectively. \"Interpretation\" can stack up to **3[i]** time(s). When using the Enhanced Skill, resets the number of \"Interpretation\" stacks on the primary target to 1. After the enemy target leaves the field or gets defeated by any unit, \"Interpretation\" will be transferred, prioritizing the transfer to Elite-level targets and above.",
			"avatar": 1401,
			"type": 2,
			"pos": {
				"point": "04",
				"prePoint": []
			},
			"icon": "spriteoutput/skillicons/avatar/1401/SkillIcon_1401_Passive.png",
			"shortIcon": "SkillIcon_1401_Passive",
			"promotion": {
				"2": 652500,
				"241": 2,
				"110201": 3,
				"110202": 15,
				"110203": 30,
				"110506": 3,
				"111001": 9,
				"111002": 13,
				"111003": 7
			},
			"params": [
				0.1,
				0.05,
				42,
				1,
				42,
				25
			],
			"requiredLevel": 0,
			"requiredPromotion": 6,
			"status": [],
			"baseSkill": [
				140104
			],
			"id": "1401004"
		},
		{
			"name": "Vibe Checker",
			"description": "After using Technique, increases The Herta's ATK by **1[i]%** at the start of the next battle, lasting for **2[i]** turn(s).\nIf there are Basic Treasures in this current map, using Technique can mark up to **3[i]** Basic Treasures' locations.\nAfter entering battle by using Technique in Simulated Universe or Divergent Universe, at the start of each wave, deals **True DMG** to enemy targets lower than Elite-level by an amount equal to **4[i]%** of the targets' Max HP, and deals **True DMG** to enemy targets at Elite-level and above by an amount equal to **5[i]%** of the targets' Max HP.",
			"avatar": 1401,
			"type": 2,
			"pos": {
				"point": "05",
				"prePoint": []
			},
			"icon": "spriteoutput/skillicons/avatar/1401/SkillIcon_1401_Maze.png",
			"shortIcon": "SkillIcon_1401_Maze",
			"promotion": {},
			"params": [
				0.6,
				2,
				3,
				0.99,
				0.3,
				25
			],
			"requiredLevel": 0,
			"requiredPromotion": 0,
			"status": [],
			"baseSkill": [
				140107
			],
			"id": "1401007"
		},
		{
			"name": "Aloofly Honest",
			"description": "When ally targets attack, inflicts 1 stack of \"Interpretation\" on the hit enemy target. After attacking, for every 1 target hit by this attack, regenerates **3** fixed Energy for The Herta, counting up to a maximum of 5 targets. When using Enhanced Skill, if the primary target's \"Interpretation\" stack reaches **42**, increases the Ice DMG dealt by The Herta by **50%**, lasting until the end of this attack.",
			"avatar": 1401,
			"type": 3,
			"pos": {
				"point": "06",
				"prePoint": []
			},
			"icon": "spriteoutput/skillicons/avatar/1401/SkillIcon_1401_SkillTree1.png",
			"shortIcon": "SkillIcon_1401_SkillTree1",
			"promotion": {
				"2": 5000,
				"110201": 3,
				"110506": 1
			},
			"params": [
				3,
				0.5
			],
			"requiredLevel": 0,
			"requiredPromotion": 2,
			"status": [],
			"baseSkill": [],
			"id": "1401101"
		},
		{
			"name": "Message From Beyond the Veil",
			"description": "When entering battle, if the team has 2 or more Erudition characters, increases all allies' CRIT DMG by **80%**. And the Trace \"Aloofly Honest\" counts at least **3** target(s) when calculating the number of targets hit. After attacking, applies **1** \"Interpretation\" stack(s) to the target that has the highest existing \"Interpretation\" stacks among the hit enemy targets. If the attacker is an Erudition character, then additionally applies **2** \"Interpretation\" stack(s).",
			"avatar": 1401,
			"type": 3,
			"pos": {
				"point": "07",
				"prePoint": []
			},
			"icon": "spriteoutput/skillicons/avatar/1401/SkillIcon_1401_SkillTree2.png",
			"shortIcon": "SkillIcon_1401_SkillTree2",
			"promotion": {
				"2": 20000,
				"241": 1,
				"110202": 5,
				"110506": 1
			},
			"params": [
				0.8,
				3,
				1,
				2
			],
			"requiredLevel": 0,
			"requiredPromotion": 4,
			"status": [],
			"baseSkill": [],
			"id": "1401102"
		},
		{
			"name": "Starved Landscape of Vacua",
			"description": "For every 1 stack of \"Interpretation\" inflicted on enemy targets, The Herta gains 1 stack of \"Answer,\" up to a max of **99** stack(s). When using Ultimate, each \"Answer\" stack increases this instance of Ultimate's DMG multiplier by **1%**.",
			"avatar": 1401,
			"type": 3,
			"pos": {
				"point": "08",
				"prePoint": []
			},
			"icon": "spriteoutput/skillicons/avatar/1401/SkillIcon_1401_SkillTree3.png",
			"shortIcon": "SkillIcon_1401_SkillTree3",
			"promotion": {
				"2": 160000,
				"241": 1,
				"110203": 8,
				"110506": 1
			},
			"params": [
				0.01,
				99
			],
			"requiredLevel": 0,
			"requiredPromotion": 6,
			"status": [],
			"baseSkill": [],
			"id": "1401103"
		},
		{
			"name": "DMG Boost: Ice",
			"description": "",
			"avatar": 1401,
			"type": 1,
			"pos": {
				"point": "09",
				"prePoint": []
			},
			"icon": "spriteoutput/ui/avatar/icon/IconIceAddedRatio.png",
			"shortIcon": "IconIceAddedRatio",
			"promotion": {
				"2": 2500,
				"111001": 2
			},
			"params": [],
			"requiredLevel": 1,
			"requiredPromotion": 0,
			"status": [
				{
					"PropertyType": "IceAddedRatio",
					"Value": 0.032
				}
			],
			"baseSkill": [],
			"id": "1401201"
		},
		{
			"name": "ATK Boost",
			"description": "",
			"avatar": 1401,
			"type": 1,
			"pos": {
				"point": "10",
				"prePoint": [
					1401101
				]
			},
			"icon": "spriteoutput/ui/avatar/icon/IconAttack.png",
			"shortIcon": "IconAttack",
			"promotion": {
				"2": 5000,
				"110201": 3,
				"111001": 6
			},
			"params": [],
			"requiredLevel": 0,
			"requiredPromotion": 2,
			"status": [
				{
					"PropertyType": "AttackAddedRatio",
					"Value": 0.04
				}
			],
			"baseSkill": [],
			"id": "1401202"
		},
		{
			"name": "DMG Boost: Ice",
			"description": "",
			"avatar": 1401,
			"type": 1,
			"pos": {
				"point": "11",
				"prePoint": [
					1401202
				]
			},
			"icon": "spriteoutput/ui/avatar/icon/IconIceAddedRatio.png",
			"shortIcon": "IconIceAddedRatio",
			"promotion": {
				"2": 10000,
				"110202": 3,
				"111002": 3
			},
			"params": [],
			"requiredLevel": 0,
			"requiredPromotion": 3,
			"status": [
				{
					"PropertyType": "IceAddedRatio",
					"Value": 0.032
				}
			],
			"baseSkill": [],
			"id": "1401203"
		},
		{
			"name": "SPD Boost",
			"description": "",
			"avatar": 1401,
			"type": 1,
			"pos": {
				"point": "12",
				"prePoint": [
					1401202
				]
			},
			"icon": "spriteoutput/ui/avatar/icon/IconSpeed.png",
			"shortIcon": "IconSpeed",
			"promotion": {
				"2": 10000,
				"110202": 3,
				"111002": 3
			},
			"params": [],
			"requiredLevel": 0,
			"requiredPromotion": 3,
			"status": [
				{
					"PropertyType": "SpeedDelta",
					"Value": 2
				}
			],
			"baseSkill": [],
			"id": "1401204"
		},
		{
			"name": "DMG Boost: Ice",
			"description": "",
			"avatar": 1401,
			"type": 1,
			"pos": {
				"point": "13",
				"prePoint": [
					1401102
				]
			},
			"icon": "spriteoutput/ui/avatar/icon/IconIceAddedRatio.png",
			"shortIcon": "IconIceAddedRatio",
			"promotion": {
				"2": 20000,
				"110202": 5,
				"111002": 4
			},
			"params": [],
			"requiredLevel": 0,
			"requiredPromotion": 4,
			"status": [
				{
					"PropertyType": "IceAddedRatio",
					"Value": 0.048
				}
			],
			"baseSkill": [],
			"id": "1401205"
		},
		{
			"name": "ATK Boost",
			"description": "",
			"avatar": 1401,
			"type": 1,
			"pos": {
				"point": "14",
				"prePoint": [
					1401205
				]
			},
			"icon": "spriteoutput/ui/avatar/icon/IconAttack.png",
			"shortIcon": "IconAttack",
			"promotion": {
				"2": 45000,
				"110203": 3,
				"111003": 3
			},
			"params": [],
			"requiredLevel": 0,
			"requiredPromotion": 5,
			"status": [
				{
					"PropertyType": "AttackAddedRatio",
					"Value": 0.06
				}
			],
			"baseSkill": [],
			"id": "1401206"
		},
		{
			"name": "DMG Boost: Ice",
			"description": "",
			"avatar": 1401,
			"type": 1,
			"pos": {
				"point": "15",
				"prePoint": [
					1401205
				]
			},
			"icon": "spriteoutput/ui/avatar/icon/IconIceAddedRatio.png",
			"shortIcon": "IconIceAddedRatio",
			"promotion": {
				"2": 45000,
				"110203": 3,
				"111003": 3
			},
			"params": [],
			"requiredLevel": 0,
			"requiredPromotion": 5,
			"status": [
				{
					"PropertyType": "IceAddedRatio",
					"Value": 0.048
				}
			],
			"baseSkill": [],
			"id": "1401207"
		},
		{
			"name": "SPD Boost",
			"description": "",
			"avatar": 1401,
			"type": 1,
			"pos": {
				"point": "16",
				"prePoint": [
					1401103
				]
			},
			"icon": "spriteoutput/ui/avatar/icon/IconSpeed.png",
			"shortIcon": "IconSpeed",
			"promotion": {
				"2": 160000,
				"110203": 8,
				"111003": 8
			},
			"params": [],
			"requiredLevel": 0,
			"requiredPromotion": 6,
			"status": [
				{
					"PropertyType": "SpeedDelta",
					"Value": 3
				}
			],
			"baseSkill": [],
			"id": "1401208"
		},
		{
			"name": "ATK Boost",
			"description": "",
			"avatar": 1401,
			"type": 1,
			"pos": {
				"point": "17",
				"prePoint": [
					1401103
				]
			},
			"icon": "spriteoutput/ui/avatar/icon/IconAttack.png",
			"shortIcon": "IconAttack",
			"promotion": {
				"2": 160000,
				"110203": 8,
				"111003": 8
			},
			"params": [],
			"requiredLevel": 75,
			"requiredPromotion": 0,
			"status": [
				{
					"PropertyType": "AttackAddedRatio",
					"Value": 0.08
				}
			],
			"baseSkill": [],
			"id": "1401209"
		},
		{
			"name": "DMG Boost: Ice",
			"description": "",
			"avatar": 1401,
			"type": 1,
			"pos": {
				"point": "18",
				"prePoint": []
			},
			"icon": "spriteoutput/ui/avatar/icon/IconIceAddedRatio.png",
			"shortIcon": "IconIceAddedRatio",
			"promotion": {
				"2": 160000,
				"110203": 8,
				"111003": 8
			},
			"params": [],
			"requiredLevel": 80,
			"requiredPromotion": 0,
			"status": [
				{
					"PropertyType": "IceAddedRatio",
					"Value": 0.064
				}
			],
			"baseSkill": [],
			"id": "1401210"
		}
	],
	"ranks": [
		{
			"name": "Night at Shorefall",
			"description": "When the Enhanced Skill calculates the number of \"Interpretation\" stacks, additionally counts <unbreak>#1[i]%</unbreak> of the number of \"Interpretation\" stacks on the 1 target with the most stacks among the primary target and adjacent targets. When \"Interpretation\" is reset by using the Enhanced Skill, its stack number is reset to <unbreak>#2[i]</unbreak> instead.",
			"icon": "spriteoutput/skillicons/avatar/1401/SkillIcon_1401_Rank1.png",
			"rankIcon": "spriteoutput/textures/1401/1401_Rank_1.png",
			"shortIcon": "SkillIcon_1401_Rank1",
			"params": [
				0.5,
				15
			],
			"skillUpgrades": {},
			"id": "140101"
		},
		{
			"name": "Wind Through Keyhole",
			"description": "After The Herta enters battle or uses Ultimate, additionally gains 1 \"Inspiration\" stack. After using Enhanced Skill, <u>advances</u> The Herta's next action by <unbreak>#1[i]%</unbreak>.",
			"icon": "spriteoutput/skillicons/avatar/1401/SkillIcon_1401_Rank2.png",
			"rankIcon": "spriteoutput/textures/1401/1401_Rank_2.png",
			"shortIcon": "SkillIcon_1401_Rank2",
			"params": [
				0.35,
				42,
				0.25
			],
			"skillUpgrades": {},
			"id": "140102"
		},
		{
			"name": "Door into Summer",
			"description": "Skill Lv. +2, up to a maximum of Lv. <unbreak>15</unbreak>.\\nTalent Lv. +2, up to a maximum of Lv. <unbreak>15</unbreak>.",
			"icon": "spriteoutput/skillicons/avatar/1401/SkillIcon_1401_BP.png",
			"rankIcon": "spriteoutput/textures/1401/1401_Rank_3.png",
			"shortIcon": "SkillIcon_1401_BP",
			"params": [],
			"skillUpgrades": {
				"140102": 2,
				"140104": 2,
				"140109": 2
			},
			"id": "140103"
		},
		{
			"name": "The Sixteenth Key",
			"description": "The SPD of Erudition characters in the team increases by <unbreak>#1[i]%</unbreak>.",
			"icon": "spriteoutput/skillicons/avatar/1401/SkillIcon_1401_Rank4.png",
			"rankIcon": "spriteoutput/textures/1401/1401_Rank_4.png",
			"shortIcon": "SkillIcon_1401_Rank4",
			"params": [
				0.12
			],
			"skillUpgrades": {},
			"id": "140104"
		},
		{
			"name": "Bitter Pill of Truth",
			"description": "Ultimate Lv. +2, up to a maximum of Lv. <unbreak>15</unbreak>.\\nBasic ATK Lv. +1, up to a maximum of Lv. <unbreak>10</unbreak>.",
			"icon": "spriteoutput/skillicons/avatar/1401/SkillIcon_1401_Ultra.png",
			"rankIcon": "spriteoutput/textures/1401/1401_Rank_5.png",
			"shortIcon": "SkillIcon_1401_Ultra",
			"params": [],
			"skillUpgrades": {
				"140101": 1,
				"140103": 2
			},
			"id": "140105"
		},
		{
			"name": "Sweet Lure of Answer",
			"description": "The Herta's Ice RES PEN increases by <unbreak>#4[i]%</unbreak>. When the number of enemy targets on the field is 3 (or more)/2/1, Ultimate's DMG multiplier increases by <unbreak>#1[i]%</unbreak>/<unbreak>#2[i]%</unbreak>/<unbreak>#3[i]%</unbreak> respectively.",
			"icon": "spriteoutput/skillicons/avatar/1401/SkillIcon_1401_Rank6.png",
			"rankIcon": "spriteoutput/textures/1401/1401_Rank_6.png",
			"shortIcon": "SkillIcon_1401_Rank6",
			"params": [
				1.4,
				2.5,
				4,
				0.2
			],
			"skillUpgrades": {},
			"id": "140106"
		}
	],
	"statsArray": [
		{
			"HPBase": 158.4,
			"HPAdd": 7.92,
			"AttackBase": 92.4,
			"AttackAdd": 4.62,
			"DefenceBase": 66,
			"DefenceAdd": 3.3,
			"SpeedBase": 99,
			"SpeedAdd": 0,
			"AggroBase": 75,
			"PromotionCostList": [
				{
					"ItemID": 2,
					"ItemNum": 4000
				},
				{
					"ItemID": 111001,
					"ItemNum": 5
				}
			],
			"MaxLevel": 20
		},
		{
			"HPBase": 221.76,
			"HPAdd": 7.92,
			"AttackBase": 129.36,
			"AttackAdd": 4.62,
			"DefenceBase": 92.4,
			"DefenceAdd": 3.3,
			"SpeedBase": 99,
			"SpeedAdd": 0,
			"AggroBase": 75,
			"PromotionCostList": [
				{
					"ItemID": 2,
					"ItemNum": 8000
				},
				{
					"ItemID": 111001,
					"ItemNum": 10
				}
			],
			"MaxLevel": 30
		},
		{
			"HPBase": 285.12,
			"HPAdd": 7.92,
			"AttackBase": 166.32,
			"AttackAdd": 4.62,
			"DefenceBase": 118.8,
			"DefenceAdd": 3.3,
			"SpeedBase": 99,
			"SpeedAdd": 0,
			"AggroBase": 75,
			"PromotionCostList": [
				{
					"ItemID": 2,
					"ItemNum": 16000
				},
				{
					"ItemID": 111002,
					"ItemNum": 6
				},
				{
					"ItemID": 110423,
					"ItemNum": 3
				}
			],
			"MaxLevel": 40
		},
		{
			"HPBase": 348.48,
			"HPAdd": 7.92,
			"AttackBase": 203.28,
			"AttackAdd": 4.62,
			"DefenceBase": 145.2,
			"DefenceAdd": 3.3,
			"SpeedBase": 99,
			"SpeedAdd": 0,
			"AggroBase": 75,
			"PromotionCostList": [
				{
					"ItemID": 2,
					"ItemNum": 40000
				},
				{
					"ItemID": 111002,
					"ItemNum": 9
				},
				{
					"ItemID": 110423,
					"ItemNum": 7
				}
			],
			"MaxLevel": 50
		},
		{
			"HPBase": 411.84,
			"HPAdd": 7.92,
			"AttackBase": 240.24,
			"AttackAdd": 4.62,
			"DefenceBase": 171.6,
			"DefenceAdd": 3.3,
			"SpeedBase": 99,
			"SpeedAdd": 0,
			"AggroBase": 75,
			"PromotionCostList": [
				{
					"ItemID": 2,
					"ItemNum": 80000
				},
				{
					"ItemID": 111003,
					"ItemNum": 6
				},
				{
					"ItemID": 110423,
					"ItemNum": 20
				}
			],
			"MaxLevel": 60
		},
		{
			"HPBase": 475.2,
			"HPAdd": 7.92,
			"AttackBase": 277.2,
			"AttackAdd": 4.62,
			"DefenceBase": 198,
			"DefenceAdd": 3.3,
			"SpeedBase": 99,
			"SpeedAdd": 0,
			"AggroBase": 75,
			"PromotionCostList": [
				{
					"ItemID": 2,
					"ItemNum": 160000
				},
				{
					"ItemID": 111003,
					"ItemNum": 9
				},
				{
					"ItemID": 110423,
					"ItemNum": 35
				}
			],
			"MaxLevel": 70
		},
		{
			"HPBase": 538.56,
			"HPAdd": 7.92,
			"AttackBase": 314.16,
			"AttackAdd": 4.62,
			"DefenceBase": 224.4,
			"DefenceAdd": 3.3,
			"SpeedBase": 99,
			"SpeedAdd": 0,
			"AggroBase": 75,
			"PromotionCostList": [],
			"MaxLevel": 80
		}
	],
	"advancement": {
		"lv0": [
			{
				"ItemID": 2,
				"ItemNum": 4000
			},
			{
				"ItemID": 111001,
				"ItemNum": 5
			}
		],
		"lv1": [
			{
				"ItemID": 2,
				"ItemNum": 8000
			},
			{
				"ItemID": 111001,
				"ItemNum": 10
			}
		],
		"lv2": [
			{
				"ItemID": 2,
				"ItemNum": 16000
			},
			{
				"ItemID": 111002,
				"ItemNum": 6
			},
			{
				"ItemID": 110423,
				"ItemNum": 3
			}
		],
		"lv3": [
			{
				"ItemID": 2,
				"ItemNum": 40000
			},
			{
				"ItemID": 111002,
				"ItemNum": 9
			},
			{
				"ItemID": 110423,
				"ItemNum": 7
			}
		],
		"lv4": [
			{
				"ItemID": 2,
				"ItemNum": 80000
			},
			{
				"ItemID": 111003,
				"ItemNum": 6
			},
			{
				"ItemID": 110423,
				"ItemNum": 20
			}
		],
		"lv5": [
			{
				"ItemID": 2,
				"ItemNum": 160000
			},
			{
				"ItemID": 111003,
				"ItemNum": 9
			},
			{
				"ItemID": 110423,
				"ItemNum": 35
			}
		]
	},
	"id": "1401"
}